gxl_ai_utils/audio_dataset/__init__.py
gxl_ai_utils/audio_dataset/build_vocab.py
gxl_ai_utils/audio_dataset/common_data_handler.py
gxl_ai_utils/audio_dataset/gxl_data_handler.py
gxl_ai_utils/audio_dataset/classify/__init__.py
gxl_ai_utils/audio_dataset/classify/data_handler.py
gxl_ai_utils/audio_dataset/recognition/__init__.py
gxl_ai_utils/audio_dataset/recognition/data_handler.py
gxl_ai_utils/audio_handler/__init__.py
gxl_ai_utils/audio_model/__init__.py
gxl_ai_utils/audio_model/classify/__init__.py
gxl_ai_utils/audio_model/classify/ecapa_tdnn.py
gxl_ai_utils/audio_model/classify/xvector.py
gxl_ai_utils/audio_model/s2t/__init__.py
gxl_ai_utils/audio_model/s2t/deepspeech2/__init__.py
gxl_ai_utils/audio_model/s2t/deepspeech2/deepspeech2.py
gxl_ai_utils/audio_model/s2t/modules/__init__.py
gxl_ai_utils/audio_model/s2t/modules/ctc_decoder.py
gxl_ai_utils/audio_model/s2t/modules/embedding.py
gxl_ai_utils/audio_model/s2t/modules/subsampling.py
gxl_ai_utils/audio_model/s2t/transformer/__init__.py
gxl_ai_utils/audio_model/s2t/transformer/transformer.py
gxl_ai_utils/audio_model/s2t/transformer/model/__init__.py
gxl_ai_utils/audio_model/s2t/transformer/model/decoder.py
gxl_ai_utils/audio_model/s2t/transformer/model/encoder.py
gxl_ai_utils/audio_model/s2t/transformer/model/competition/__init__.py
gxl_ai_utils/audio_model/s2t/transformer/model/competition/multi_head_attention.py
gxl_ai_utils/audio_model/s2t/transformer/model/competition/positional_encoding.py
gxl_ai_utils/audio_model/s2t/transformer/model/competition/positional_wise_feed_forward.py
gxl_ai_utils/audio_model/s2t/transformer/model/competition/scaled_dot_product_attention.py
gxl_ai_utils/audio_model/s2t/transformer/model/utils/__init__.py
gxl_ai_utils/audio_model/s2t/transformer/model/utils/padding_mask.py
gxl_ai_utils/audio_model/s2t/transformer/model/utils/sequence_mask.py
gxl_ai_utils/audio_model/s2t/utils/__init__.py
gxl_ai_utils/audio_model/s2t/utils/ctc_utils.py
gxl_ai_utils/audio_model/t2s/__init__.py
gxl_ai_utils-1.6.1.dist-info/METADATA
gxl_ai_utils-1.6.1.dist-info/WHEEL
gxl_ai_utils-1.6.1.dist-info/top_level.txt
gxl_ai_utils-1.6.1.dist-info/RECORD
