Metadata-Version: 2.4
Name: gxl_ai_utils
Version: 1.6.1
Summary: 这个是耿雪龙的工具包模块，更新： add func: do_files_identical, update time: 2025-11.10
Author: Xuelong Geng
Author-email: 3349495429@qq.com
Requires-Dist: jsonlines
Requires-Dist: colorama
Requires-Dist: tqdm
Dynamic: author
Dynamic: author-email
Dynamic: requires-dist
Dynamic: summary
